conch/__init__.py
conch/_version.py
conch/exceptions.py
conch/io.py
conch/main.py
conch/multiprocessing.py
conch/threading.py
conch/utils.py
conch/analysis/__init__.py
conch/analysis/autovot.py
conch/analysis/functions.py
conch/analysis/gammatone.py
conch/analysis/helper.py
conch/analysis/praat.py
conch/analysis/segments.py
conch/analysis/specgram.py
conch/analysis/amplitude_envelopes/__init__.py
conch/analysis/amplitude_envelopes/amplitude_envelopes.py
conch/analysis/formants/__init__.py
conch/analysis/formants/formant_point.praat
conch/analysis/formants/formant_point_segment.praat
conch/analysis/formants/formant_track.praat
conch/analysis/formants/formant_track_segment.praat
conch/analysis/formants/lpc.py
conch/analysis/formants/praat.py
conch/analysis/intensity/__init__.py
conch/analysis/intensity/intensity_track.praat
conch/analysis/intensity/intensity_track_segment.praat
conch/analysis/intensity/praat.py
conch/analysis/mfcc/__init__.py
conch/analysis/mfcc/mfcc.praat
conch/analysis/mfcc/praat.py
conch/analysis/mfcc/rastamat.py
conch/analysis/pitch/__init__.py
conch/analysis/pitch/autocorrelation.py
conch/analysis/pitch/pitch_track.praat
conch/analysis/pitch/pitch_track_segment.praat
conch/analysis/pitch/pitch_track_with_pulses.praat
conch/analysis/pitch/pitch_track_with_pulses_segment.praat
conch/analysis/pitch/praat.py
conch/analysis/pitch/reaper.py
conch/distance/__init__.py
conch/distance/base.py
conch/distance/dct.py
conch/distance/dtw.py
conch/distance/point.py
conch/distance/xcorr.py
conch_sounds-0.4.2.dist-info/licenses/LICENSE
conch_sounds-0.4.2.dist-info/METADATA
conch_sounds-0.4.2.dist-info/WHEEL
conch_sounds-0.4.2.dist-info/top_level.txt
conch_sounds-0.4.2.dist-info/RECORD
