Metadata-Version: 2.4
Name: Conch-sounds
Version: 0.4.2
Summary: Analyze acoustic similarity in Python
Home-page: https://github.com/mmcauliffe/Conch-sounds
Author: Michael McAuliffe
Author-email: michael.e.mcauliffe@gmail.com
Maintainer: Michael McAuliffe
Maintainer-email: michael.e.mcauliffe@gmail.com
License: MIT
Keywords: phonetics,acoustics,acoustic similarity
Classifier: Development Status :: 3 - Alpha
Classifier: Programming Language :: Python
Classifier: Programming Language :: Python :: 3
Classifier: Operating System :: OS Independent
Classifier: Topic :: Scientific/Engineering
Classifier: Topic :: Text Processing :: Linguistic
Requires-Python: >=3.8
License-File: LICENSE
Requires-Dist: numpy
Requires-Dist: librosa
Requires-Dist: scipy
Requires-Dist: praatio
Requires-Dist: pyraat
Provides-Extra: dev
Requires-Dist: coverage; extra == "dev"
Requires-Dist: coveralls; extra == "dev"
Requires-Dist: interrogate; extra == "dev"
Requires-Dist: pytest; extra == "dev"
Requires-Dist: pytest-mypy; extra == "dev"
Requires-Dist: setuptools-scm; extra == "dev"
Requires-Dist: tomli; extra == "dev"
Requires-Dist: tox; extra == "dev"
Requires-Dist: tox-conda; extra == "dev"
Provides-Extra: docs
Requires-Dist: interrogate; extra == "docs"
Requires-Dist: numpydoc; extra == "docs"
Requires-Dist: pydata-sphinx-theme; extra == "docs"
Requires-Dist: sphinx; extra == "docs"
Requires-Dist: sphinx-design; extra == "docs"
Provides-Extra: testing
Requires-Dist: coverage; extra == "testing"
Requires-Dist: coveralls; extra == "testing"
Requires-Dist: pytest; extra == "testing"
Dynamic: license-file
